{
    "Ar36": {
        "error": 0.004700965242156349, 
        "filter_outliers_dict": {
            "filter_outliers": true, 
            "iterations": 2, 
            "std_devs": 2
        }, 
        "fit": "Parabolic", 
        "value": 4.124193124176011
    }, 
    "Ar37": {
        "error": 0.012438941860657478, 
        "filter_outliers_dict": {
            "filter_outliers": true, 
            "iterations": 2, 
            "std_devs": 2
        }, 
        "fit": "linear", 
        "value": 0.04170015729084376
    }, 
    "Ar38": {
        "error": 0.013157370122920361, 
        "filter_outliers_dict": {
            "filter_outliers": true, 
            "iterations": 2, 
            "std_devs": 2
        }, 
        "fit": "linear", 
        "value": 0.6452530310101391
    }, 
    "Ar39": {
        "error": 0.0249495981680938, 
        "filter_outliers_dict": {
            "filter_outliers": true, 
            "iterations": 2, 
            "std_devs": 2
        }, 
        "fit": "Parabolic", 
        "value": 0.04453550249240144
    }, 
    "Ar40": {
        "error": 0.08992379124960685, 
        "filter_outliers_dict": {
            "filter_outliers": true, 
            "iterations": 2, 
            "std_devs": 2
        }, 
        "fit": "Parabolic", 
        "value": 1218.6307166023234
    }
}